README.rst
asyncwsgi.py
setup.py
asyncwsgi.egg-info/PKG-INFO
asyncwsgi.egg-info/SOURCES.txt
asyncwsgi.egg-info/dependency_links.txt
asyncwsgi.egg-info/requires.txt
asyncwsgi.egg-info/top_level.txt