Metadata-Version: 1.1
Name: asyncwsgi
Version: 0.1.0
Summary: Async WSGI support for tornado and asyncio
Home-page: https://github.com/nehz/asyncwsgi
Author: Zhen Wang
Author-email: mail@zhenwang.info
License: MIT
Download-URL: https://github.com/nehz/asyncwsgi/archive/asyncwsgi-0.1.0.tar.gz
Platform: UNKNOWN
